potato_communicate/__init__.py
potato_communicate/client.py
potato_communicate/converter.py
potato_communicate/server.py
potato_communicate-1.0.2.dist-info/METADATA
potato_communicate-1.0.2.dist-info/WHEEL
potato_communicate-1.0.2.dist-info/top_level.txt
potato_communicate-1.0.2.dist-info/RECORD
