Metadata-Version: 2.1
Name: potato-communicate
Version: 1.0.2
Summary: 跨平台通讯框架PotatoCommunicate的python端
Home-page: UNKNOWN
Author: thtTNT
License: UNKNOWN
Platform: UNKNOWN
Requires-Python: >=3.8
